<annotation>
	<folder>dent</folder>
	<filename>59.jpg</filename>
	<path>C:\Users\x_gui\Desktop\Ramos\Feria\TFODCourse-main\Tensorflow\workspace\images\collectedimages\dent\59.jpg</path>
	<source>
		<database>Unknown</database>
	</source>
	<size>
		<width>1024</width>
		<height>1024</height>
		<depth>3</depth>
	</size>
	<segmented>0</segmented>
	<object>
		<name>dent</name>
		<pose>Unspecified</pose>
		<truncated>0</truncated>
		<difficult>0</difficult>
		<bndbox>
			<xmin>284</xmin>
			<ymin>299</ymin>
			<xmax>541</xmax>
			<ymax>504</ymax>
		</bndbox>
	</object>
	<object>
		<name>scratch</name>
		<pose>Unspecified</pose>
		<truncated>0</truncated>
		<difficult>0</difficult>
		<bndbox>
			<xmin>368</xmin>
			<ymin>473</ymin>
			<xmax>839</xmax>
			<ymax>932</ymax>
		</bndbox>
	</object>
</annotation>
